[{"id": 3112570009830756846, "name": "Mahwish", "email": "Mahwish@gmail.com", "movies": {"16010507862308688000": {"id": 16010507862308688000, "name": "Titanic", "director": "James Cameron", "year": "1997", "rating": 7.9, "poster_url": "https://m.media-amazon.com/images/M/MV5BMDdmZGU3NDQtY2E5My00ZTliLWIzOTUtMTY4ZGI1YjdiNjk3XkEyXkFqcGdeQXVyNTA4NzY1MzY@._V1_SX300.jpg", "imdbID": "tt0120338"}, "14958777144405266926": {"id": 14958777144405266926, "name": "Spiderman", "director": "Christian Davi", "year": "1990", "rating": 5.6, "poster_url": "", "imdbID": "tt0100669"}, "10840208450220593646": {"id": 10840208450220593646, "name": "Gladiator 2", "director": "Ridley Scott", "year": "2024", "rating": 0.0, "poster_url": "https://m.media-amazon.com/images/M/MV5BYTNmMzliMmYtNjEyZS00NGM3LWEzYWEtNmI3MGJjMTIzZjI4XkEyXkFqcGdeQXVyMTI3NjAxODc0._V1_SX300.jpg", "imdbID": "tt9218128"}}}, {"id": 14576307987414782446, "name": "Shubham", "email": "ssing163@binghamton.edu", "movies": {}}]